{
  "success": true,
  "query": "plush bear with roses bouquet teddy gift romantic",
  "count": 20,
  "ranked": false,
  "results": [
    {
      "original_url": "https://sfile.chatglm.cn/images-ppt/c67068680bce.jpg",
      "caption": "",
      "source": "Amazon.com",
      "original_width": "894px",
      "original_height": "882px"
    },
    {
      "original_url": "https://sfile.chatglm.cn/images-ppt/58cff287a2f7.jpg",
      "caption": "",
      "source": "Amazon.com",
      "original_width": "1600px",
      "original_height": "1600px"
    },
    {
      "original_url": "https://sfile.chatglm.cn/images-ppt/0ad482b4a739.jpg",
      "caption": "",
      "source": "Vermont Teddy Bear",
      "original_width": "1946px",
      "original_height": "1946px"
    },
    {
      "original_url": "https://sfile.chatglm.cn/images-ppt/8f46e699ece3.jpg",
      "caption": "",
      "source": "Amazon.com",
      "original_width": "1600px",
      "original_height": "1600px"
    },
    {
      "original_url": "https://sfile.chatglm.cn/images-ppt/d52a5699054d.jpeg",
      "caption": "",
      "source": "Walmart",
      "original_width": "1600px",
      "original_height": "1600px"
    },
    {
      "original_url": "https://sfile.chatglm.cn/images-ppt/eaa58ea98a01.png",
      "caption": "",
      "source": "new jersey blooms",
      "original_width": "1000px",
      "original_height": "1000px"
    },
    {
      "original_url": "https://sfile.chatglm.cn/images-ppt/901a43c3ca79.jpg",
      "caption": "",
      "source": "Amazon.com",
      "original_width": "894px",
      "original_height": "894px"
    },
    {
      "original_url": "https://sfile.chatglm.cn/images-ppt/2da583d99fa2.jpg",
      "caption": "",
      "source": "Amazon.com",
      "original_width": "1600px",
      "original_height": "1600px"
    },
    {
      "original_url": "https://sfile.chatglm.cn/images-ppt/93d88fd7f922.png",
      "caption": "",
      "source": "los angeles blooms",
      "original_width": "1000px",
      "original_height": "1000px"
    },
    {
      "original_url": "https://sfile.chatglm.cn/images-ppt/e9d70b581b17.jpeg",
      "caption": "",
      "source": "Walmart",
      "original_width": "1600px",
      "original_height": "1600px"
    },
    {
      "original_url": "https://sfile.chatglm.cn/images-ppt/0469a264e078.jpg",
      "caption": "",
      "source": "Montejo's Florist",
      "original_width": "1005px",
      "original_height": "2048px"
    },
    {
      "original_url": "https://sfile.chatglm.cn/images-ppt/0cca50e6c799.jpg",
      "caption": "",
      "source": "Flower Delivery by Las Palmas Flowers & Party Supplies",
      "original_width": "1280px",
      "original_height": "1280px"
    },
    {
      "original_url": "https://sfile.chatglm.cn/images-ppt/1027da1b44fd.webp",
      "caption": "",
      "source": "Miami Flower Delivery",
      "original_width": "1026px",
      "original_height": "1026px"
    },
    {
      "original_url": "https://sfile.chatglm.cn/images-ppt/d4fbcba57ab6.jpg",
      "caption": "",
      "source": "Amazon.in",
      "original_width": "1000px",
      "original_height": "1000px"
    },
    {
      "original_url": "https://sfile.chatglm.cn/images-ppt/56287476c111.jpg",
      "caption": "",
      "source": "Giftmandu",
      "original_width": "1280px",
      "original_height": "1280px"
    },
    {
      "original_url": "https://sfile.chatglm.cn/images-ppt/2424a489e24f.jpg",
      "caption": "",
      "source": "Florist Chennai",
      "original_width": "1000px",
      "original_height": "1000px"
    },
    {
      "original_url": "https://sfile.chatglm.cn/images-ppt/95cbc192b040.jpeg",
      "caption": "",
      "source": "Flowersome Store",
      "original_width": "1320px",
      "original_height": "1324px"
    },
    {
      "original_url": "https://sfile.chatglm.cn/images-ppt/d83964c01f19.jpg",
      "caption": "",
      "source": "Basketeer",
      "original_width": "960px",
      "original_height": "1100px"
    },
    {
      "original_url": "https://sfile.chatglm.cn/images-ppt/83ed5146c5d1.jpg",
      "caption": "",
      "source": "Giftmandu",
      "original_width": "1280px",
      "original_height": "1280px"
    },
    {
      "original_url": "https://sfile.chatglm.cn/images-ppt/4e3848eb7118.jpg",
      "caption": "",
      "source": "BELLASSOM FLORAL STUDIO",
      "original_width": "1500px",
      "original_height": "1500px"
    }
  ]
}
